{
    "crags": {
        "Stanage_Edge": {
            "name": "Stanage_Edge",
            "location": "S32",
            "difficultyMin": 20,
            "difficultyMax": 42,
            "rockMaterial": "limestone"
        },
        "Froggatt_Edge": {
            "name": "Froggatt_Edge",
            "location": "S32",
            "difficultyMin": 18,
            "difficultyMax": 39,
            "rockMaterial": "granite"
        },
        "Curbar_Edge": {
            "name": "Curbar_Edge",
            "location": "S32",
            "difficultyMin": 24,
            "difficultyMax": 49,
            "rockMaterial": "sandstone"
        },
        "Burbage_North": {
            "name": "Curbar_Edge",
            "location": "S32",
            "difficultyMin": 29,
            "difficultyMax": 56,
            "rockMaterial": "gneiss"
        },
        "Burbage_South": {
            "name": "Burbage_North",
            "location": "S32",
            "difficultyMin": 19,
            "difficultyMax": 52,
            "rockMaterial": "basalt"
        },
        "Milstone_Edge": {
            "name": "Milstone_Edge",
            "location": "S32",
            "difficultyMin": 32,
            "difficultyMax": 60,
            "rockMaterial": "limestone"
        },
        "Birchen_Edge": {
            "name": "Birchen_Edge",
            "location": "DE45",
            "difficultyMin": 22,
            "difficultyMax": 47,
            "rockMaterial": "granite"
        },
        "Lawrencefield": {
            "name": "Lawrencefield",
            "location": "S32",
            "difficultyMin": 25,
            "difficultyMax": 58,
            "rockMaterial": "gneiss"
        },
        "Raven_Tor": {
            "name": "Raven_Tor",
            "location": "RG1",
            "difficultyMin": 16,
            "difficultyMax": 35,
            "rockMaterial": "sandstone"
        },
        "Dovedale": {
            "name": "Dovedale",
            "location": "DE6",
            "difficultyMin": 27,
            "difficultyMax": 53,
            "rockMaterial": "basalt"
        },
        "Chee_Dale": {
            "name": "Chee_Dale",
            "location": "CB2",
            "difficultyMin": 28,
            "difficultyMax": 59,
            "rockMaterial": "limestone"
        },
        "Malham_Cove": {
            "name": "Malham_Cove",
            "location": "LL49",
            "difficultyMin": 21,
            "difficultyMax": 46,
            "rockMaterial": "granite"
        },
        "Goredale_Scar": {
            "name": "Goredale_Scar",
            "location": "LL55",
            "difficultyMin": 18,
            "difficultyMax": 37,
            "rockMaterial": "gneiss"
        },
        "Kilnsey_Crag": {
            "name": "Kilnsey_Crag",
            "location": "LL65",
            "difficultyMin": 32,
            "difficultyMax": 50,
            "rockMaterial": "sandstone"
        },
        "Beach_Hill": {
            "name": "Beach_Hill",
            "location": "WN6",
            "difficultyMin": 26,
            "difficultyMax": 55,
            "rockMaterial": "basalt"
        }
    }
}
